[
  {
    "url": "https://twitter.com/anyuser/status/1966843351246008476",
    "repliedAt": "Sat Sep 13 16:59:32 +0000 2025"
  },
  {
    "url": "https://twitter.com/anyuser/status/1966893439838003379",
    "repliedAt": "Sat Sep 13 16:59:03 +0000 2025"
  },
  {
    "url": "https://twitter.com/anyuser/status/1966840957581881388",
    "repliedAt": "Sat Sep 13 16:56:42 +0000 2025"
  },
  {
    "url": "https://twitter.com/anyuser/status/1966835502658826442",
    "repliedAt": "Sat Sep 13 16:53:22 +0000 2025"
  },
  {
    "url": "https://twitter.com/anyuser/status/1966773443732324407",
    "repliedAt": "Sat Sep 13 16:51:36 +0000 2025"
  },
  {
    "url": "https://twitter.com/anyuser/status/1966778843118633436",
    "repliedAt": "Sat Sep 13 16:51:30 +0000 2025"
  },
  {
    "url": "https://twitter.com/anyuser/status/1966885689263558710",
    "repliedAt": "Sat Sep 13 16:49:37 +0000 2025"
  },
  {
    "url": "https://twitter.com/anyuser/status/1966542975695282474",
    "repliedAt": "Sat Sep 13 16:48:52 +0000 2025"
  },
  {
    "url": "https://twitter.com/anyuser/status/1966887830925557773",
    "repliedAt": "Sat Sep 13 16:48:29 +0000 2025"
  },
  {
    "url": "https://twitter.com/anyuser/status/1966864197825814755",
    "repliedAt": "Sat Sep 13 16:46:33 +0000 2025"
  },
  {
    "url": "https://twitter.com/anyuser/status/1966879747759321521",
    "repliedAt": "Sat Sep 13 16:46:10 +0000 2025"
  },
  {
    "url": "https://twitter.com/anyuser/status/1966871408035946935",
    "repliedAt": "Sat Sep 13 16:45:37 +0000 2025"
  },
  {
    "url": "https://twitter.com/anyuser/status/1966887093537567027",
    "repliedAt": "Sat Sep 13 16:45:19 +0000 2025"
  },
  {
    "url": "https://twitter.com/anyuser/status/1966897090669547861",
    "repliedAt": "Sat Sep 13 16:44:59 +0000 2025"
  },
  {
    "url": "https://twitter.com/anyuser/status/1966895808063959483",
    "repliedAt": "Sat Sep 13 16:44:41 +0000 2025"
  },
  {
    "url": "https://twitter.com/anyuser/status/1966876242491429151",
    "repliedAt": "Sat Sep 13 16:43:52 +0000 2025"
  },
  {
    "url": "https://twitter.com/anyuser/status/1966534605344797140",
    "repliedAt": "Sat Sep 13 16:40:34 +0000 2025"
  },
  {
    "url": "https://twitter.com/anyuser/status/1966877910775840920",
    "repliedAt": "Sat Sep 13 16:40:12 +0000 2025"
  },
  {
    "url": "https://twitter.com/anyuser/status/1966880399755444700",
    "repliedAt": "Sat Sep 13 16:39:52 +0000 2025"
  },
  {
    "url": "https://twitter.com/anyuser/status/1966837133416804770",
    "repliedAt": "Sat Sep 13 16:38:30 +0000 2025"
  },
  {
    "url": "https://twitter.com/anyuser/status/1966874299543024064",
    "repliedAt": "Sat Sep 13 16:38:02 +0000 2025"
  },
  {
    "url": "https://twitter.com/anyuser/status/1966838379976241223",
    "repliedAt": "Sat Sep 13 16:37:42 +0000 2025"
  },
  {
    "url": "https://twitter.com/anyuser/status/1966837411511677247",
    "repliedAt": "Sat Sep 13 16:37:03 +0000 2025"
  },
  {
    "url": "https://twitter.com/anyuser/status/1966882820405796873",
    "repliedAt": "Sat Sep 13 16:36:45 +0000 2025"
  },
  {
    "url": "https://twitter.com/anyuser/status/1966874194828030290",
    "repliedAt": "Sat Sep 13 16:35:51 +0000 2025"
  },
  {
    "url": "https://twitter.com/anyuser/status/1966853596886020389",
    "repliedAt": "Sat Sep 13 16:35:35 +0000 2025"
  },
  {
    "url": "https://twitter.com/anyuser/status/1966850253631680514",
    "repliedAt": "Sat Sep 13 16:34:58 +0000 2025"
  },
  {
    "url": "https://twitter.com/anyuser/status/1966872747977695333",
    "repliedAt": "Sat Sep 13 16:34:31 +0000 2025"
  },
  {
    "url": "https://twitter.com/anyuser/status/1966835538109100066",
    "repliedAt": "Sat Sep 13 16:34:11 +0000 2025"
  },
  {
    "url": "https://twitter.com/anyuser/status/1966866221288354161",
    "repliedAt": "Sat Sep 13 16:33:52 +0000 2025"
  },
  {
    "url": "https://twitter.com/anyuser/status/1966889855314481270",
    "repliedAt": "Sat Sep 13 16:33:30 +0000 2025"
  },
  {
    "url": "https://twitter.com/anyuser/status/1966895600479449204",
    "repliedAt": "Sat Sep 13 16:32:34 +0000 2025"
  },
  {
    "url": "https://twitter.com/anyuser/status/1966901487516467482",
    "repliedAt": "Sat Sep 13 16:31:47 +0000 2025"
  },
  {
    "url": "https://twitter.com/anyuser/status/1966696044567130213",
    "repliedAt": "Sat Sep 13 16:25:01 +0000 2025"
  },
  {
    "url": "https://twitter.com/anyuser/status/1966651782349677025",
    "repliedAt": "Sat Sep 13 16:23:36 +0000 2025"
  },
  {
    "url": "https://twitter.com/anyuser/status/1966733651975995473",
    "repliedAt": "Sat Sep 13 16:21:24 +0000 2025"
  },
  {
    "url": "https://twitter.com/anyuser/status/1966621430734377062",
    "repliedAt": "Sat Sep 13 16:20:40 +0000 2025"
  },
  {
    "url": "https://twitter.com/anyuser/status/1966742738386157878",
    "repliedAt": "Sat Sep 13 16:12:18 +0000 2025"
  },
  {
    "url": "https://twitter.com/anyuser/status/1966893424591650936",
    "repliedAt": "Sat Sep 13 16:04:12 +0000 2025"
  },
  {
    "url": "https://twitter.com/anyuser/status/1966893429344137433",
    "repliedAt": "Sat Sep 13 16:02:30 +0000 2025"
  },
  {
    "url": "https://twitter.com/anyuser/status/1966892292201214203",
    "repliedAt": "Sat Sep 13 15:51:33 +0000 2025"
  },
  {
    "url": "https://twitter.com/anyuser/status/1966796713609371795",
    "repliedAt": "Sat Sep 13 15:50:03 +0000 2025"
  },
  {
    "url": "https://twitter.com/anyuser/status/1966567652060443012",
    "repliedAt": "Sat Sep 13 15:45:09 +0000 2025"
  },
  {
    "url": "https://twitter.com/anyuser/status/1966862667429093822",
    "repliedAt": "Sat Sep 13 15:44:41 +0000 2025"
  },
  {
    "url": "https://twitter.com/anyuser/status/1966881495756439580",
    "repliedAt": "Sat Sep 13 15:41:42 +0000 2025"
  },
  {
    "url": "https://twitter.com/anyuser/status/1966623310474621185",
    "repliedAt": "Sat Sep 13 15:40:23 +0000 2025"
  },
  {
    "url": "https://twitter.com/anyuser/status/1966885966594842705",
    "repliedAt": "Sat Sep 13 15:40:22 +0000 2025"
  },
  {
    "url": "https://twitter.com/anyuser/status/1966152420926554143",
    "repliedAt": "Sat Sep 13 15:39:38 +0000 2025"
  },
  {
    "url": "https://twitter.com/anyuser/status/1966696197415940334",
    "repliedAt": "Sat Sep 13 15:39:17 +0000 2025"
  },
  {
    "url": "https://twitter.com/anyuser/status/1966694344179462618",
    "repliedAt": "Sat Sep 13 15:37:54 +0000 2025"
  },
  {
    "url": "https://twitter.com/anyuser/status/1966887407867089177",
    "repliedAt": "Sat Sep 13 15:35:52 +0000 2025"
  },
  {
    "url": "https://twitter.com/anyuser/status/1966882644433793351",
    "repliedAt": "Sat Sep 13 15:30:15 +0000 2025"
  },
  {
    "url": "https://twitter.com/anyuser/status/1966883873893347838",
    "repliedAt": "Sat Sep 13 15:29:27 +0000 2025"
  },
  {
    "url": "https://twitter.com/anyuser/status/1966851274714009935",
    "repliedAt": "Sat Sep 13 15:28:44 +0000 2025"
  },
  {
    "url": "https://twitter.com/anyuser/status/1966871399483810045",
    "repliedAt": "Sat Sep 13 15:28:10 +0000 2025"
  },
  {
    "url": "https://twitter.com/anyuser/status/1966511573574287464",
    "repliedAt": "Sat Sep 13 15:26:51 +0000 2025"
  },
  {
    "url": "https://twitter.com/anyuser/status/1966620882052546955",
    "repliedAt": "Sat Sep 13 15:24:45 +0000 2025"
  },
  {
    "url": "https://twitter.com/anyuser/status/1966879552916869223",
    "repliedAt": "Sat Sep 13 15:17:38 +0000 2025"
  },
  {
    "url": "https://twitter.com/anyuser/status/1966879555207188563",
    "repliedAt": "Sat Sep 13 15:16:55 +0000 2025"
  },
  {
    "url": "https://twitter.com/anyuser/status/1966577239719383344",
    "repliedAt": "Sat Sep 13 15:16:29 +0000 2025"
  },
  {
    "url": "https://twitter.com/anyuser/status/1966879759553753365",
    "repliedAt": "Sat Sep 13 15:15:12 +0000 2025"
  },
  {
    "url": "https://twitter.com/anyuser/status/1966712132969353241",
    "repliedAt": "Sat Sep 13 15:13:40 +0000 2025"
  },
  {
    "url": "https://twitter.com/anyuser/status/1966880288082194541",
    "repliedAt": "Sat Sep 13 15:13:00 +0000 2025"
  },
  {
    "url": "https://twitter.com/anyuser/status/1966880504638304696",
    "repliedAt": "Sat Sep 13 15:12:18 +0000 2025"
  },
  {
    "url": "https://twitter.com/anyuser/status/1966880713766060295",
    "repliedAt": "Sat Sep 13 15:08:36 +0000 2025"
  },
  {
    "url": "https://twitter.com/anyuser/status/1966738479615766748",
    "repliedAt": "Sat Sep 13 15:06:20 +0000 2025"
  },
  {
    "url": "https://twitter.com/anyuser/status/1966864443859476857",
    "repliedAt": "Sat Sep 13 14:43:38 +0000 2025"
  },
  {
    "url": "https://twitter.com/anyuser/status/1966837636951400850",
    "repliedAt": "Sat Sep 13 14:42:36 +0000 2025"
  },
  {
    "url": "https://twitter.com/anyuser/status/1966871704598450240",
    "repliedAt": "Sat Sep 13 14:41:56 +0000 2025"
  },
  {
    "url": "https://twitter.com/anyuser/status/1966870343177605289",
    "repliedAt": "Sat Sep 13 14:39:36 +0000 2025"
  },
  {
    "url": "https://twitter.com/anyuser/status/1966868932390010960",
    "repliedAt": "Sat Sep 13 14:38:59 +0000 2025"
  },
  {
    "url": "https://twitter.com/anyuser/status/1966869958811677125",
    "repliedAt": "Sat Sep 13 14:38:24 +0000 2025"
  },
  {
    "url": "https://twitter.com/anyuser/status/1966870203331211657",
    "repliedAt": "Sat Sep 13 14:37:49 +0000 2025"
  },
  {
    "url": "https://twitter.com/anyuser/status/1966856896024895540",
    "repliedAt": "Sat Sep 13 14:36:08 +0000 2025"
  },
  {
    "url": "https://twitter.com/anyuser/status/1966852759405400287",
    "repliedAt": "Sat Sep 13 14:26:42 +0000 2025"
  },
  {
    "url": "https://twitter.com/anyuser/status/1966651828067856609",
    "repliedAt": "Sat Sep 13 14:21:54 +0000 2025"
  },
  {
    "url": "https://twitter.com/anyuser/status/1966865072132956213",
    "repliedAt": "Sat Sep 13 14:20:00 +0000 2025"
  },
  {
    "url": "https://twitter.com/anyuser/status/1966868218112602592",
    "repliedAt": "Sat Sep 13 14:19:21 +0000 2025"
  },
  {
    "url": "https://twitter.com/anyuser/status/1966696680251641932",
    "repliedAt": "Sat Sep 13 14:17:54 +0000 2025"
  },
  {
    "url": "https://twitter.com/anyuser/status/1966580682026557503",
    "repliedAt": "Sat Sep 13 14:12:20 +0000 2025"
  },
  {
    "url": "https://twitter.com/anyuser/status/1966789952391573713",
    "repliedAt": "Sat Sep 13 13:53:01 +0000 2025"
  },
  {
    "url": "https://twitter.com/anyuser/status/1966635143885418879",
    "repliedAt": "Sat Sep 13 13:48:09 +0000 2025"
  },
  {
    "url": "https://twitter.com/anyuser/status/1966819082264834257",
    "repliedAt": "Sat Sep 13 13:47:48 +0000 2025"
  },
  {
    "url": "https://twitter.com/anyuser/status/1966720885626118514",
    "repliedAt": "Sat Sep 13 13:47:09 +0000 2025"
  },
  {
    "url": "https://twitter.com/anyuser/status/1966499985203015733",
    "repliedAt": "Sat Sep 13 13:46:49 +0000 2025"
  },
  {
    "url": "https://twitter.com/anyuser/status/1966621769420148765",
    "repliedAt": "Sat Sep 13 13:46:35 +0000 2025"
  },
  {
    "url": "https://twitter.com/anyuser/status/1966546258408911069",
    "repliedAt": "Sat Sep 13 13:46:31 +0000 2025"
  },
  {
    "url": "https://twitter.com/anyuser/status/1966499169587077125",
    "repliedAt": "Sat Sep 13 13:45:31 +0000 2025"
  },
  {
    "url": "https://twitter.com/anyuser/status/1966577235311071614",
    "repliedAt": "Sat Sep 13 13:45:05 +0000 2025"
  },
  {
    "url": "https://twitter.com/anyuser/status/1966710148266684662",
    "repliedAt": "Sat Sep 13 13:43:19 +0000 2025"
  },
  {
    "url": "https://twitter.com/anyuser/status/1966232129014264118",
    "repliedAt": "Sat Sep 13 13:42:38 +0000 2025"
  },
  {
    "url": "https://twitter.com/anyuser/status/1966676560242507913",
    "repliedAt": "Sat Sep 13 13:42:20 +0000 2025"
  },
  {
    "url": "https://twitter.com/anyuser/status/1966642343190110501",
    "repliedAt": "Sat Sep 13 13:42:02 +0000 2025"
  },
  {
    "url": "https://twitter.com/anyuser/status/1966528399968469230",
    "repliedAt": "Sat Sep 13 13:41:34 +0000 2025"
  },
  {
    "url": "https://twitter.com/anyuser/status/1966671487202459977",
    "repliedAt": "Sat Sep 13 13:41:19 +0000 2025"
  },
  {
    "url": "https://twitter.com/anyuser/status/1966711401852137916",
    "repliedAt": "Sat Sep 13 13:41:07 +0000 2025"
  },
  {
    "url": "https://twitter.com/anyuser/status/1966469866308673770",
    "repliedAt": "Sat Sep 13 13:40:43 +0000 2025"
  },
  {
    "url": "https://twitter.com/anyuser/status/1966702961460920783",
    "repliedAt": "Sat Sep 13 13:40:04 +0000 2025"
  },
  {
    "url": "https://twitter.com/anyuser/status/1966651382112379099",
    "repliedAt": "Sat Sep 13 13:36:27 +0000 2025"
  },
  {
    "url": "https://twitter.com/anyuser/status/1966656783365075452",
    "repliedAt": "Sat Sep 13 13:36:11 +0000 2025"
  },
  {
    "url": "https://twitter.com/anyuser/status/1966824430186684611",
    "repliedAt": "Sat Sep 13 13:35:57 +0000 2025"
  },
  {
    "url": "https://twitter.com/anyuser/status/1966500593440039098",
    "repliedAt": "Sat Sep 13 13:30:30 +0000 2025"
  },
  {
    "url": "https://twitter.com/anyuser/status/1966796757230031204",
    "repliedAt": "Sat Sep 13 13:30:10 +0000 2025"
  },
  {
    "url": "https://twitter.com/anyuser/status/1966819146378645744",
    "repliedAt": "Sat Sep 13 13:26:42 +0000 2025"
  },
  {
    "url": "https://twitter.com/anyuser/status/1966830470563328046",
    "repliedAt": "Sat Sep 13 13:26:25 +0000 2025"
  },
  {
    "url": "https://twitter.com/anyuser/status/1966796495392567469",
    "repliedAt": "Sat Sep 13 13:25:23 +0000 2025"
  },
  {
    "url": "https://twitter.com/anyuser/status/1966184639468548119",
    "repliedAt": "Sat Sep 13 13:24:46 +0000 2025"
  },
  {
    "url": "https://twitter.com/anyuser/status/1966852869153554781",
    "repliedAt": "Sat Sep 13 13:22:24 +0000 2025"
  },
  {
    "url": "https://twitter.com/anyuser/status/1966528524010799253",
    "repliedAt": "Sat Sep 13 13:22:20 +0000 2025"
  },
  {
    "url": "https://twitter.com/anyuser/status/1966156521475280934",
    "repliedAt": "Sat Sep 13 13:22:10 +0000 2025"
  },
  {
    "url": "https://twitter.com/anyuser/status/1966850468682035556",
    "repliedAt": "Sat Sep 13 13:22:07 +0000 2025"
  },
  {
    "url": "https://twitter.com/anyuser/status/1966649275275739394",
    "repliedAt": "Sat Sep 13 13:21:09 +0000 2025"
  },
  {
    "url": "https://twitter.com/anyuser/status/1966848938570600808",
    "repliedAt": "Sat Sep 13 13:21:01 +0000 2025"
  },
  {
    "url": "https://twitter.com/anyuser/status/1966638535475093573",
    "repliedAt": "Sat Sep 13 13:20:15 +0000 2025"
  },
  {
    "url": "https://twitter.com/anyuser/status/1966545174474928472",
    "repliedAt": "Sat Sep 13 13:14:56 +0000 2025"
  },
  {
    "url": "https://twitter.com/anyuser/status/1966667250724655462",
    "repliedAt": "Sat Sep 13 13:14:54 +0000 2025"
  },
  {
    "url": "https://twitter.com/anyuser/status/1966766364179169351",
    "repliedAt": "Sat Sep 13 13:14:11 +0000 2025"
  },
  {
    "url": "https://twitter.com/anyuser/status/1966831524290195953",
    "repliedAt": "Sat Sep 13 13:12:09 +0000 2025"
  },
  {
    "url": "https://twitter.com/anyuser/status/1966830745755824490",
    "repliedAt": "Sat Sep 13 13:11:12 +0000 2025"
  },
  {
    "url": "https://twitter.com/anyuser/status/1966832337897091276",
    "repliedAt": "Sat Sep 13 13:10:09 +0000 2025"
  },
  {
    "url": "https://twitter.com/anyuser/status/1966691051139445125",
    "repliedAt": "Sat Sep 13 13:06:23 +0000 2025"
  },
  {
    "url": "https://twitter.com/anyuser/status/1966548366524895333",
    "repliedAt": "Sat Sep 13 13:04:50 +0000 2025"
  },
  {
    "url": "https://twitter.com/anyuser/status/1966826259289108809",
    "repliedAt": "Sat Sep 13 13:03:45 +0000 2025"
  },
  {
    "url": "https://twitter.com/anyuser/status/1966753640934490118",
    "repliedAt": "Sat Sep 13 13:02:29 +0000 2025"
  },
  {
    "url": "https://twitter.com/anyuser/status/1966594322700070937",
    "repliedAt": "Sat Sep 13 12:57:39 +0000 2025"
  },
  {
    "url": "https://twitter.com/anyuser/status/1966658776003461269",
    "repliedAt": "Sat Sep 13 12:56:49 +0000 2025"
  },
  {
    "url": "https://twitter.com/anyuser/status/1966687137463758962",
    "repliedAt": "Sat Sep 13 12:56:05 +0000 2025"
  },
  {
    "url": "https://twitter.com/anyuser/status/1966755581655740539",
    "repliedAt": "Sat Sep 13 12:55:38 +0000 2025"
  },
  {
    "url": "https://twitter.com/anyuser/status/1966721527073612145",
    "repliedAt": "Sat Sep 13 12:55:04 +0000 2025"
  },
  {
    "url": "https://twitter.com/anyuser/status/1966575347471712303",
    "repliedAt": "Sat Sep 13 12:54:36 +0000 2025"
  },
  {
    "url": "https://twitter.com/anyuser/status/1966668148272205992",
    "repliedAt": "Sat Sep 13 12:54:08 +0000 2025"
  },
  {
    "url": "https://twitter.com/anyuser/status/1966828577720344757",
    "repliedAt": "Sat Sep 13 12:52:11 +0000 2025"
  },
  {
    "url": "https://twitter.com/anyuser/status/1966641727281733877",
    "repliedAt": "Sat Sep 13 12:51:21 +0000 2025"
  },
  {
    "url": "https://twitter.com/anyuser/status/1966833500377796726",
    "repliedAt": "Sat Sep 13 12:48:35 +0000 2025"
  },
  {
    "url": "https://twitter.com/anyuser/status/1966840811544605157",
    "repliedAt": "Sat Sep 13 12:44:25 +0000 2025"
  },
  {
    "url": "https://twitter.com/anyuser/status/1966836106021707908",
    "repliedAt": "Sat Sep 13 12:42:36 +0000 2025"
  },
  {
    "url": "https://twitter.com/anyuser/status/1966834793695637558",
    "repliedAt": "Sat Sep 13 12:42:07 +0000 2025"
  },
  {
    "url": "https://twitter.com/anyuser/status/1966775209916330022",
    "repliedAt": "Sat Sep 13 12:41:31 +0000 2025"
  },
  {
    "url": "https://twitter.com/anyuser/status/1966579934421205216",
    "repliedAt": "Sat Sep 13 12:40:55 +0000 2025"
  },
  {
    "url": "https://twitter.com/anyuser/status/1966604608567906319",
    "repliedAt": "Sat Sep 13 12:39:56 +0000 2025"
  },
  {
    "url": "https://twitter.com/anyuser/status/1966721284827402244",
    "repliedAt": "Sat Sep 13 12:38:00 +0000 2025"
  },
  {
    "url": "https://twitter.com/anyuser/status/1966823330079494167",
    "repliedAt": "Sat Sep 13 12:37:46 +0000 2025"
  },
  {
    "url": "https://twitter.com/anyuser/status/1966721533843251308",
    "repliedAt": "Sat Sep 13 12:37:12 +0000 2025"
  },
  {
    "url": "https://twitter.com/anyuser/status/1966626626713907366",
    "repliedAt": "Sat Sep 13 12:36:59 +0000 2025"
  },
  {
    "url": "https://twitter.com/anyuser/status/1966486956856275083",
    "repliedAt": "Sat Sep 13 12:34:31 +0000 2025"
  },
  {
    "url": "https://twitter.com/anyuser/status/1966583934231224755",
    "repliedAt": "Sat Sep 13 12:32:26 +0000 2025"
  },
  {
    "url": "https://twitter.com/anyuser/status/1966584985227325886",
    "repliedAt": "Sat Sep 13 12:31:09 +0000 2025"
  },
  {
    "url": "https://twitter.com/anyuser/status/1966577553973670298",
    "repliedAt": "Sat Sep 13 12:30:58 +0000 2025"
  },
  {
    "url": "https://twitter.com/anyuser/status/1966632063211078027",
    "repliedAt": "Sat Sep 13 12:29:29 +0000 2025"
  },
  {
    "url": "https://twitter.com/anyuser/status/1966484731932835872",
    "repliedAt": "Sat Sep 13 12:29:09 +0000 2025"
  },
  {
    "url": "https://twitter.com/anyuser/status/1966785170994065850",
    "repliedAt": "Sat Sep 13 12:28:48 +0000 2025"
  },
  {
    "url": "https://twitter.com/anyuser/status/1966729320824487988",
    "repliedAt": "Sat Sep 13 12:28:40 +0000 2025"
  },
  {
    "url": "https://twitter.com/anyuser/status/1966834870623367685",
    "repliedAt": "Sat Sep 13 12:28:31 +0000 2025"
  },
  {
    "url": "https://twitter.com/anyuser/status/1966835707890315369",
    "repliedAt": "Sat Sep 13 12:27:55 +0000 2025"
  },
  {
    "url": "https://twitter.com/anyuser/status/1966718057868374030",
    "repliedAt": "Sat Sep 13 12:26:23 +0000 2025"
  },
  {
    "url": "https://twitter.com/anyuser/status/1966611491278246149",
    "repliedAt": "Sat Sep 13 12:24:51 +0000 2025"
  },
  {
    "url": "https://twitter.com/anyuser/status/1966735936680542616",
    "repliedAt": "Sat Sep 13 12:23:39 +0000 2025"
  },
  {
    "url": "https://twitter.com/anyuser/status/1966559429131661362",
    "repliedAt": "Sat Sep 13 12:23:35 +0000 2025"
  },
  {
    "url": "https://twitter.com/anyuser/status/1966705020964905227",
    "repliedAt": "Sat Sep 13 12:23:29 +0000 2025"
  },
  {
    "url": "https://twitter.com/anyuser/status/1966597427172876702",
    "repliedAt": "Sat Sep 13 12:22:30 +0000 2025"
  },
  {
    "url": "https://twitter.com/anyuser/status/1966521513990889546",
    "repliedAt": "Sat Sep 13 12:21:56 +0000 2025"
  },
  {
    "url": "https://twitter.com/anyuser/status/1966834942052380747",
    "repliedAt": "Sat Sep 13 12:21:45 +0000 2025"
  },
  {
    "url": "https://twitter.com/anyuser/status/1966578845693235534",
    "repliedAt": "Sat Sep 13 12:21:08 +0000 2025"
  },
  {
    "url": "https://twitter.com/anyuser/status/1966834845193257125",
    "repliedAt": "Sat Sep 13 12:20:43 +0000 2025"
  },
  {
    "url": "https://twitter.com/anyuser/status/1966683789754499465",
    "repliedAt": "Sat Sep 13 12:20:37 +0000 2025"
  },
  {
    "url": "https://twitter.com/anyuser/status/1966791193259372698",
    "repliedAt": "Sat Sep 13 12:20:35 +0000 2025"
  },
  {
    "url": "https://twitter.com/anyuser/status/1966788353505796273",
    "repliedAt": "Sat Sep 13 12:19:57 +0000 2025"
  },
  {
    "url": "https://twitter.com/anyuser/status/1966677312037904542",
    "repliedAt": "Sat Sep 13 12:15:15 +0000 2025"
  },
  {
    "url": "https://twitter.com/anyuser/status/1940520843446309228",
    "repliedAt": "Sat Sep 13 12:12:52 +0000 2025"
  },
  {
    "url": "https://twitter.com/anyuser/status/1966834472537506241",
    "repliedAt": "Sat Sep 13 12:09:18 +0000 2025"
  },
  {
    "url": "https://twitter.com/anyuser/status/1966836037566501038",
    "repliedAt": "Sat Sep 13 12:09:18 +0000 2025"
  },
  {
    "url": "https://twitter.com/anyuser/status/1966707952363917433",
    "repliedAt": "Sat Sep 13 12:08:33 +0000 2025"
  },
  {
    "url": "https://twitter.com/anyuser/status/1966798735792288150",
    "repliedAt": "Sat Sep 13 12:07:32 +0000 2025"
  },
  {
    "url": "https://twitter.com/anyuser/status/1966834089207755137",
    "repliedAt": "Sat Sep 13 12:07:30 +0000 2025"
  },
  {
    "url": "https://twitter.com/anyuser/status/1966551002363945304",
    "repliedAt": "Sat Sep 13 12:07:05 +0000 2025"
  },
  {
    "url": "https://twitter.com/anyuser/status/1966797567838011407",
    "repliedAt": "Sat Sep 13 12:03:44 +0000 2025"
  },
  {
    "url": "https://twitter.com/anyuser/status/1966832987489636844",
    "repliedAt": "Sat Sep 13 12:01:22 +0000 2025"
  },
  {
    "url": "https://twitter.com/anyuser/status/1966795443494678726",
    "repliedAt": "Sat Sep 13 12:00:56 +0000 2025"
  },
  {
    "url": "https://twitter.com/anyuser/status/1966623859135730031",
    "repliedAt": "Sat Sep 13 11:59:51 +0000 2025"
  },
  {
    "url": "https://twitter.com/anyuser/status/1966600989210730938",
    "repliedAt": "Sat Sep 13 11:57:27 +0000 2025"
  },
  {
    "url": "https://twitter.com/anyuser/status/1966808757561946367",
    "repliedAt": "Sat Sep 13 11:56:20 +0000 2025"
  },
  {
    "url": "https://twitter.com/anyuser/status/1966566434697527624",
    "repliedAt": "Sat Sep 13 11:55:42 +0000 2025"
  },
  {
    "url": "https://twitter.com/anyuser/status/1966829267364561216",
    "repliedAt": "Sat Sep 13 11:54:47 +0000 2025"
  },
  {
    "url": "https://twitter.com/anyuser/status/1966800056511529315",
    "repliedAt": "Sat Sep 13 11:54:45 +0000 2025"
  },
  {
    "url": "https://twitter.com/anyuser/status/1966630988198339049",
    "repliedAt": "Sat Sep 13 11:48:51 +0000 2025"
  },
  {
    "url": "https://twitter.com/anyuser/status/1966830308734705710",
    "repliedAt": "Sat Sep 13 11:46:45 +0000 2025"
  },
  {
    "url": "https://twitter.com/anyuser/status/1966538416092246495",
    "repliedAt": "Sat Sep 13 11:45:42 +0000 2025"
  },
  {
    "url": "https://twitter.com/anyuser/status/1966782963636728267",
    "repliedAt": "Sat Sep 13 11:44:52 +0000 2025"
  },
  {
    "url": "https://twitter.com/anyuser/status/1966744149874405586",
    "repliedAt": "Sat Sep 13 11:44:18 +0000 2025"
  },
  {
    "url": "https://twitter.com/anyuser/status/1966595844666232864",
    "repliedAt": "Sat Sep 13 11:43:36 +0000 2025"
  },
  {
    "url": "https://twitter.com/anyuser/status/1966754153658556616",
    "repliedAt": "Sat Sep 13 11:40:42 +0000 2025"
  },
  {
    "url": "https://twitter.com/anyuser/status/1966814345108824346",
    "repliedAt": "Sat Sep 13 11:39:32 +0000 2025"
  },
  {
    "url": "https://twitter.com/anyuser/status/1966821692824842512",
    "repliedAt": "Sat Sep 13 11:38:43 +0000 2025"
  },
  {
    "url": "https://twitter.com/anyuser/status/1966502303550050320",
    "repliedAt": "Sat Sep 13 11:38:21 +0000 2025"
  },
  {
    "url": "https://twitter.com/anyuser/status/1966822286612459944",
    "repliedAt": "Sat Sep 13 11:35:25 +0000 2025"
  },
  {
    "url": "https://twitter.com/anyuser/status/1966819530363060731",
    "repliedAt": "Sat Sep 13 11:34:31 +0000 2025"
  },
  {
    "url": "https://twitter.com/anyuser/status/1966826697228951690",
    "repliedAt": "Sat Sep 13 11:33:45 +0000 2025"
  },
  {
    "url": "https://twitter.com/anyuser/status/1966818986999382475",
    "repliedAt": "Sat Sep 13 11:33:29 +0000 2025"
  },
  {
    "url": "https://twitter.com/anyuser/status/1966810321512767552",
    "repliedAt": "Sat Sep 13 11:32:32 +0000 2025"
  },
  {
    "url": "https://twitter.com/anyuser/status/1966552343425520112",
    "repliedAt": "Sat Sep 13 11:31:11 +0000 2025"
  }
]