[
  {
    "url": "https://twitter.com/anyuser/status/1966202740037791962",
    "repliedAt": "Fri Sep 12 00:58:00 +0000 2025"
  },
  {
    "url": "https://twitter.com/anyuser/status/1966187199365525807",
    "repliedAt": "Fri Sep 12 00:55:38 +0000 2025"
  },
  {
    "url": "https://twitter.com/anyuser/status/1966232868964999210",
    "repliedAt": "Fri Sep 12 00:55:13 +0000 2025"
  },
  {
    "url": "https://twitter.com/anyuser/status/1966241507461181899",
    "repliedAt": "Fri Sep 12 00:45:26 +0000 2025"
  },
  {
    "url": "https://twitter.com/anyuser/status/1966240406133416315",
    "repliedAt": "Fri Sep 12 00:44:54 +0000 2025"
  },
  {
    "url": "https://twitter.com/anyuser/status/1966245428837650634",
    "repliedAt": "Fri Sep 12 00:44:18 +0000 2025"
  },
  {
    "url": "https://twitter.com/anyuser/status/1966209242118885826",
    "repliedAt": "Fri Sep 12 00:43:52 +0000 2025"
  },
  {
    "url": "https://twitter.com/anyuser/status/1966144063616499813",
    "repliedAt": "Fri Sep 12 00:38:54 +0000 2025"
  },
  {
    "url": "https://twitter.com/anyuser/status/1966270834408120446",
    "repliedAt": "Fri Sep 12 00:29:39 +0000 2025"
  },
  {
    "url": "https://twitter.com/anyuser/status/1966271816231788568",
    "repliedAt": "Fri Sep 12 00:29:03 +0000 2025"
  },
  {
    "url": "https://twitter.com/anyuser/status/1966189639913582682",
    "repliedAt": "Fri Sep 12 00:26:12 +0000 2025"
  },
  {
    "url": "https://twitter.com/anyuser/status/1966204004159066380",
    "repliedAt": "Fri Sep 12 00:25:44 +0000 2025"
  },
  {
    "url": "https://twitter.com/anyuser/status/1966258246743949784",
    "repliedAt": "Fri Sep 12 00:24:27 +0000 2025"
  },
  {
    "url": "https://twitter.com/anyuser/status/1966247903137247724",
    "repliedAt": "Fri Sep 12 00:24:03 +0000 2025"
  },
  {
    "url": "https://twitter.com/anyuser/status/1966273243486237141",
    "repliedAt": "Fri Sep 12 00:23:26 +0000 2025"
  },
  {
    "url": "https://twitter.com/anyuser/status/1966256971134234678",
    "repliedAt": "Fri Sep 12 00:22:45 +0000 2025"
  },
  {
    "url": "https://twitter.com/anyuser/status/1966239403308888102",
    "repliedAt": "Fri Sep 12 00:21:41 +0000 2025"
  },
  {
    "url": "https://twitter.com/anyuser/status/1966264506486853810",
    "repliedAt": "Fri Sep 12 00:20:22 +0000 2025"
  },
  {
    "url": "https://twitter.com/anyuser/status/1966254220090495359",
    "repliedAt": "Fri Sep 12 00:19:44 +0000 2025"
  },
  {
    "url": "https://twitter.com/anyuser/status/1966247030579409127",
    "repliedAt": "Fri Sep 12 00:16:58 +0000 2025"
  },
  {
    "url": "https://twitter.com/anyuser/status/1966248780145242287",
    "repliedAt": "Fri Sep 12 00:12:38 +0000 2025"
  },
  {
    "url": "https://twitter.com/anyuser/status/1966254540082016659",
    "repliedAt": "Fri Sep 12 00:12:03 +0000 2025"
  },
  {
    "url": "https://twitter.com/anyuser/status/1966250135308087660",
    "repliedAt": "Fri Sep 12 00:11:23 +0000 2025"
  },
  {
    "url": "https://twitter.com/anyuser/status/1966276607162847284",
    "repliedAt": "Fri Sep 12 00:10:48 +0000 2025"
  },
  {
    "url": "https://twitter.com/anyuser/status/1966267907551408262",
    "repliedAt": "Fri Sep 12 00:09:13 +0000 2025"
  },
  {
    "url": "https://twitter.com/anyuser/status/1966108974454911084",
    "repliedAt": "Fri Sep 12 00:07:27 +0000 2025"
  },
  {
    "url": "https://twitter.com/anyuser/status/1966193545922097313",
    "repliedAt": "Fri Sep 12 00:06:12 +0000 2025"
  },
  {
    "url": "https://twitter.com/anyuser/status/1966189043261247674",
    "repliedAt": "Fri Sep 12 00:03:10 +0000 2025"
  },
  {
    "url": "https://twitter.com/anyuser/status/1966198131282030625",
    "repliedAt": "Thu Sep 11 23:59:47 +0000 2025"
  },
  {
    "url": "https://twitter.com/anyuser/status/1966198209522671928",
    "repliedAt": "Thu Sep 11 23:58:20 +0000 2025"
  },
  {
    "url": "https://twitter.com/anyuser/status/1966184069206597651",
    "repliedAt": "Thu Sep 11 23:57:23 +0000 2025"
  },
  {
    "url": "https://twitter.com/anyuser/status/1966172351638417848",
    "repliedAt": "Thu Sep 11 23:56:26 +0000 2025"
  },
  {
    "url": "https://twitter.com/anyuser/status/1966276370432143384",
    "repliedAt": "Thu Sep 11 23:52:35 +0000 2025"
  },
  {
    "url": "https://twitter.com/anyuser/status/1966285246732628467",
    "repliedAt": "Thu Sep 11 23:52:06 +0000 2025"
  },
  {
    "url": "https://twitter.com/anyuser/status/1966275351597691367",
    "repliedAt": "Thu Sep 11 23:51:24 +0000 2025"
  },
  {
    "url": "https://twitter.com/anyuser/status/1966274976853655580",
    "repliedAt": "Thu Sep 11 23:50:08 +0000 2025"
  },
  {
    "url": "https://twitter.com/anyuser/status/1966195465948381227",
    "repliedAt": "Thu Sep 11 23:32:39 +0000 2025"
  },
  {
    "url": "https://twitter.com/anyuser/status/1966184593226346693",
    "repliedAt": "Thu Sep 11 23:31:54 +0000 2025"
  },
  {
    "url": "https://twitter.com/anyuser/status/1966209616011813348",
    "repliedAt": "Thu Sep 11 23:31:27 +0000 2025"
  },
  {
    "url": "https://twitter.com/anyuser/status/1966137915630833878",
    "repliedAt": "Thu Sep 11 23:13:59 +0000 2025"
  },
  {
    "url": "https://twitter.com/anyuser/status/1966172525869818034",
    "repliedAt": "Thu Sep 11 23:13:26 +0000 2025"
  },
  {
    "url": "https://twitter.com/anyuser/status/1966191886177361972",
    "repliedAt": "Thu Sep 11 23:12:44 +0000 2025"
  },
  {
    "url": "https://twitter.com/anyuser/status/1966171389104370073",
    "repliedAt": "Thu Sep 11 23:11:44 +0000 2025"
  },
  {
    "url": "https://twitter.com/anyuser/status/1966193657113182361",
    "repliedAt": "Thu Sep 11 23:10:21 +0000 2025"
  },
  {
    "url": "https://twitter.com/anyuser/status/1966197836934156693",
    "repliedAt": "Thu Sep 11 23:09:15 +0000 2025"
  },
  {
    "url": "https://twitter.com/anyuser/status/1966166251597709601",
    "repliedAt": "Thu Sep 11 23:08:34 +0000 2025"
  },
  {
    "url": "https://twitter.com/anyuser/status/1966174170565513434",
    "repliedAt": "Thu Sep 11 23:07:03 +0000 2025"
  },
  {
    "url": "https://twitter.com/anyuser/status/1966169520403525760",
    "repliedAt": "Thu Sep 11 23:06:14 +0000 2025"
  },
  {
    "url": "https://twitter.com/anyuser/status/1966175941467718114",
    "repliedAt": "Thu Sep 11 23:05:09 +0000 2025"
  },
  {
    "url": "https://twitter.com/anyuser/status/1966204223869300977",
    "repliedAt": "Thu Sep 11 23:00:13 +0000 2025"
  },
  {
    "url": "https://twitter.com/anyuser/status/1966164687453827125",
    "repliedAt": "Thu Sep 11 22:59:12 +0000 2025"
  },
  {
    "url": "https://twitter.com/anyuser/status/1966217221346086994",
    "repliedAt": "Thu Sep 11 22:56:59 +0000 2025"
  },
  {
    "url": "https://twitter.com/anyuser/status/1966209096715297083",
    "repliedAt": "Thu Sep 11 22:55:53 +0000 2025"
  },
  {
    "url": "https://twitter.com/anyuser/status/1966199411840880708",
    "repliedAt": "Thu Sep 11 22:54:49 +0000 2025"
  },
  {
    "url": "https://twitter.com/anyuser/status/1966018953886806116",
    "repliedAt": "Thu Sep 11 22:51:12 +0000 2025"
  },
  {
    "url": "https://twitter.com/anyuser/status/1966175018024595507",
    "repliedAt": "Thu Sep 11 22:50:46 +0000 2025"
  },
  {
    "url": "https://twitter.com/anyuser/status/1966211825562955857",
    "repliedAt": "Thu Sep 11 22:49:47 +0000 2025"
  },
  {
    "url": "https://twitter.com/anyuser/status/1966222703570071567",
    "repliedAt": "Thu Sep 11 22:48:10 +0000 2025"
  },
  {
    "url": "https://twitter.com/anyuser/status/1966220328624955516",
    "repliedAt": "Thu Sep 11 22:44:52 +0000 2025"
  },
  {
    "url": "https://twitter.com/anyuser/status/1966090497576870054",
    "repliedAt": "Thu Sep 11 22:43:19 +0000 2025"
  },
  {
    "url": "https://twitter.com/anyuser/status/1966144130788032722",
    "repliedAt": "Thu Sep 11 22:42:39 +0000 2025"
  },
  {
    "url": "https://twitter.com/anyuser/status/1966223890126180595",
    "repliedAt": "Thu Sep 11 22:40:01 +0000 2025"
  },
  {
    "url": "https://twitter.com/anyuser/status/1966222607553835082",
    "repliedAt": "Thu Sep 11 22:39:17 +0000 2025"
  },
  {
    "url": "https://twitter.com/anyuser/status/1966238497645408626",
    "repliedAt": "Thu Sep 11 22:36:18 +0000 2025"
  },
  {
    "url": "https://twitter.com/anyuser/status/1966220219028005255",
    "repliedAt": "Thu Sep 11 22:29:35 +0000 2025"
  },
  {
    "url": "https://twitter.com/anyuser/status/1966216936670507349",
    "repliedAt": "Thu Sep 11 22:26:34 +0000 2025"
  },
  {
    "url": "https://twitter.com/anyuser/status/1966222508774010914",
    "repliedAt": "Thu Sep 11 22:25:59 +0000 2025"
  },
  {
    "url": "https://twitter.com/anyuser/status/1966217485067366842",
    "repliedAt": "Thu Sep 11 22:17:00 +0000 2025"
  },
  {
    "url": "https://twitter.com/anyuser/status/1966223857833890167",
    "repliedAt": "Thu Sep 11 22:16:19 +0000 2025"
  },
  {
    "url": "https://twitter.com/anyuser/status/1966225944332636501",
    "repliedAt": "Thu Sep 11 22:16:01 +0000 2025"
  },
  {
    "url": "https://twitter.com/anyuser/status/1966225858185855279",
    "repliedAt": "Thu Sep 11 21:53:13 +0000 2025"
  },
  {
    "url": "https://twitter.com/anyuser/status/1966204382242132392",
    "repliedAt": "Thu Sep 11 21:50:30 +0000 2025"
  },
  {
    "url": "https://twitter.com/anyuser/status/1966219049752531406",
    "repliedAt": "Thu Sep 11 21:49:31 +0000 2025"
  },
  {
    "url": "https://twitter.com/anyuser/status/1966225920173527458",
    "repliedAt": "Thu Sep 11 21:49:09 +0000 2025"
  },
  {
    "url": "https://twitter.com/anyuser/status/1966181613642944832",
    "repliedAt": "Thu Sep 11 21:48:05 +0000 2025"
  },
  {
    "url": "https://twitter.com/anyuser/status/1966173293616181743",
    "repliedAt": "Thu Sep 11 21:46:47 +0000 2025"
  },
  {
    "url": "https://twitter.com/anyuser/status/1966182902393418165",
    "repliedAt": "Thu Sep 11 21:45:32 +0000 2025"
  },
  {
    "url": "https://twitter.com/anyuser/status/1966171189044228563",
    "repliedAt": "Thu Sep 11 21:44:58 +0000 2025"
  },
  {
    "url": "https://twitter.com/anyuser/status/1966159460294169018",
    "repliedAt": "Thu Sep 11 21:43:25 +0000 2025"
  },
  {
    "url": "https://twitter.com/anyuser/status/1966227940779204815",
    "repliedAt": "Thu Sep 11 21:42:53 +0000 2025"
  },
  {
    "url": "https://twitter.com/anyuser/status/1966227173683114234",
    "repliedAt": "Thu Sep 11 21:41:49 +0000 2025"
  },
  {
    "url": "https://twitter.com/anyuser/status/1966224481271328800",
    "repliedAt": "Thu Sep 11 21:41:23 +0000 2025"
  },
  {
    "url": "https://twitter.com/anyuser/status/1966223433014079519",
    "repliedAt": "Thu Sep 11 21:40:52 +0000 2025"
  },
  {
    "url": "https://twitter.com/anyuser/status/1966137864749724076",
    "repliedAt": "Thu Sep 11 21:36:06 +0000 2025"
  },
  {
    "url": "https://twitter.com/anyuser/status/1966123359080690117",
    "repliedAt": "Thu Sep 11 21:30:14 +0000 2025"
  },
  {
    "url": "https://twitter.com/anyuser/status/1965996091003797637",
    "repliedAt": "Thu Sep 11 21:28:18 +0000 2025"
  },
  {
    "url": "https://twitter.com/anyuser/status/1965875375134880142",
    "repliedAt": "Thu Sep 11 21:27:43 +0000 2025"
  },
  {
    "url": "https://twitter.com/anyuser/status/1965990042679079401",
    "repliedAt": "Thu Sep 11 21:26:59 +0000 2025"
  },
  {
    "url": "https://twitter.com/anyuser/status/1965898821185188015",
    "repliedAt": "Thu Sep 11 21:26:06 +0000 2025"
  },
  {
    "url": "https://twitter.com/anyuser/status/1966015062776361011",
    "repliedAt": "Thu Sep 11 21:25:37 +0000 2025"
  },
  {
    "url": "https://twitter.com/anyuser/status/1966008897522774133",
    "repliedAt": "Thu Sep 11 21:25:30 +0000 2025"
  },
  {
    "url": "https://twitter.com/anyuser/status/1965973614165111094",
    "repliedAt": "Thu Sep 11 21:24:59 +0000 2025"
  },
  {
    "url": "https://twitter.com/anyuser/status/1965993476111179891",
    "repliedAt": "Thu Sep 11 21:24:00 +0000 2025"
  },
  {
    "url": "https://twitter.com/anyuser/status/1965892407712690638",
    "repliedAt": "Thu Sep 11 21:23:21 +0000 2025"
  },
  {
    "url": "https://twitter.com/anyuser/status/1965952908538843402",
    "repliedAt": "Thu Sep 11 21:22:55 +0000 2025"
  },
  {
    "url": "https://twitter.com/anyuser/status/1965948556629455171",
    "repliedAt": "Thu Sep 11 21:22:11 +0000 2025"
  },
  {
    "url": "https://twitter.com/anyuser/status/1966105588053717082",
    "repliedAt": "Thu Sep 11 21:21:57 +0000 2025"
  },
  {
    "url": "https://twitter.com/anyuser/status/1966245290392039843",
    "repliedAt": "Thu Sep 11 21:14:16 +0000 2025"
  },
  {
    "url": "https://twitter.com/anyuser/status/1966203911683060071",
    "repliedAt": "Thu Sep 11 21:12:57 +0000 2025"
  },
  {
    "url": "https://twitter.com/anyuser/status/1966104564031172737",
    "repliedAt": "Thu Sep 11 21:10:46 +0000 2025"
  },
  {
    "url": "https://twitter.com/anyuser/status/1965886223811219775",
    "repliedAt": "Thu Sep 11 21:09:58 +0000 2025"
  },
  {
    "url": "https://twitter.com/anyuser/status/1966229137552716129",
    "repliedAt": "Thu Sep 11 21:08:30 +0000 2025"
  },
  {
    "url": "https://twitter.com/anyuser/status/1966120004186787866",
    "repliedAt": "Thu Sep 11 21:06:55 +0000 2025"
  },
  {
    "url": "https://twitter.com/anyuser/status/1966156196869714073",
    "repliedAt": "Thu Sep 11 21:05:43 +0000 2025"
  },
  {
    "url": "https://twitter.com/anyuser/status/1966100429588279665",
    "repliedAt": "Thu Sep 11 21:05:22 +0000 2025"
  },
  {
    "url": "https://twitter.com/anyuser/status/1966176568872698334",
    "repliedAt": "Thu Sep 11 21:03:27 +0000 2025"
  },
  {
    "url": "https://twitter.com/anyuser/status/1966233577546527087",
    "repliedAt": "Thu Sep 11 21:02:14 +0000 2025"
  },
  {
    "url": "https://twitter.com/anyuser/status/1966244608289149319",
    "repliedAt": "Thu Sep 11 21:01:41 +0000 2025"
  },
  {
    "url": "https://twitter.com/anyuser/status/1966240683037163995",
    "repliedAt": "Thu Sep 11 21:00:42 +0000 2025"
  },
  {
    "url": "https://twitter.com/anyuser/status/1966231394000175160",
    "repliedAt": "Thu Sep 11 21:00:40 +0000 2025"
  },
  {
    "url": "https://twitter.com/anyuser/status/1966201229668979174",
    "repliedAt": "Thu Sep 11 20:59:52 +0000 2025"
  },
  {
    "url": "https://twitter.com/anyuser/status/1966222731558752743",
    "repliedAt": "Thu Sep 11 20:59:35 +0000 2025"
  },
  {
    "url": "https://twitter.com/anyuser/status/1966215170608529835",
    "repliedAt": "Thu Sep 11 20:59:07 +0000 2025"
  },
  {
    "url": "https://twitter.com/anyuser/status/1966237297806028978",
    "repliedAt": "Thu Sep 11 20:58:51 +0000 2025"
  },
  {
    "url": "https://twitter.com/anyuser/status/1966168999320035698",
    "repliedAt": "Thu Sep 11 20:58:20 +0000 2025"
  },
  {
    "url": "https://twitter.com/anyuser/status/1966222224043700258",
    "repliedAt": "Thu Sep 11 20:57:10 +0000 2025"
  },
  {
    "url": "https://twitter.com/anyuser/status/1966162800100913243",
    "repliedAt": "Thu Sep 11 20:56:57 +0000 2025"
  },
  {
    "url": "https://twitter.com/anyuser/status/1966236219635105983",
    "repliedAt": "Thu Sep 11 20:55:30 +0000 2025"
  },
  {
    "url": "https://twitter.com/anyuser/status/1966162664763302023",
    "repliedAt": "Thu Sep 11 20:55:17 +0000 2025"
  },
  {
    "url": "https://twitter.com/anyuser/status/1966224766752403742",
    "repliedAt": "Thu Sep 11 20:54:14 +0000 2025"
  },
  {
    "url": "https://twitter.com/anyuser/status/1966237814154256513",
    "repliedAt": "Thu Sep 11 20:53:42 +0000 2025"
  },
  {
    "url": "https://twitter.com/anyuser/status/1966237813424472229",
    "repliedAt": "Thu Sep 11 20:50:14 +0000 2025"
  },
  {
    "url": "https://twitter.com/anyuser/status/1966214189266923841",
    "repliedAt": "Thu Sep 11 20:49:16 +0000 2025"
  },
  {
    "url": "https://twitter.com/anyuser/status/1966233844346233085",
    "repliedAt": "Thu Sep 11 20:47:03 +0000 2025"
  },
  {
    "url": "https://twitter.com/anyuser/status/1966187364629491823",
    "repliedAt": "Thu Sep 11 20:45:13 +0000 2025"
  },
  {
    "url": "https://twitter.com/anyuser/status/1966219238328381943",
    "repliedAt": "Thu Sep 11 20:44:31 +0000 2025"
  },
  {
    "url": "https://twitter.com/anyuser/status/1965942652991623509",
    "repliedAt": "Thu Sep 11 20:36:28 +0000 2025"
  },
  {
    "url": "https://twitter.com/anyuser/status/1966161139349278902",
    "repliedAt": "Thu Sep 11 20:33:55 +0000 2025"
  },
  {
    "url": "https://twitter.com/anyuser/status/1965943566410072284",
    "repliedAt": "Thu Sep 11 20:25:11 +0000 2025"
  },
  {
    "url": "https://twitter.com/anyuser/status/1966079397732946110",
    "repliedAt": "Thu Sep 11 20:24:07 +0000 2025"
  },
  {
    "url": "https://twitter.com/anyuser/status/1965915192463864099",
    "repliedAt": "Thu Sep 11 20:23:55 +0000 2025"
  },
  {
    "url": "https://twitter.com/anyuser/status/1966173110350327916",
    "repliedAt": "Thu Sep 11 20:22:38 +0000 2025"
  },
  {
    "url": "https://twitter.com/anyuser/status/1965903481921003589",
    "repliedAt": "Thu Sep 11 20:22:16 +0000 2025"
  },
  {
    "url": "https://twitter.com/anyuser/status/1966196290603155564",
    "repliedAt": "Thu Sep 11 20:21:14 +0000 2025"
  },
  {
    "url": "https://twitter.com/anyuser/status/1966207848293052896",
    "repliedAt": "Thu Sep 11 20:13:43 +0000 2025"
  },
  {
    "url": "https://twitter.com/anyuser/status/1965819539603747031",
    "repliedAt": "Thu Sep 11 20:11:51 +0000 2025"
  },
  {
    "url": "https://twitter.com/anyuser/status/1966167697420595216",
    "repliedAt": "Thu Sep 11 20:10:48 +0000 2025"
  },
  {
    "url": "https://twitter.com/anyuser/status/1966113164275134890",
    "repliedAt": "Thu Sep 11 20:08:37 +0000 2025"
  },
  {
    "url": "https://twitter.com/anyuser/status/1966216470511202650",
    "repliedAt": "Thu Sep 11 20:07:51 +0000 2025"
  },
  {
    "url": "https://twitter.com/anyuser/status/1965932664470515898",
    "repliedAt": "Thu Sep 11 20:07:36 +0000 2025"
  },
  {
    "url": "https://twitter.com/anyuser/status/1966210886160527760",
    "repliedAt": "Thu Sep 11 20:07:24 +0000 2025"
  },
  {
    "url": "https://twitter.com/anyuser/status/1966220865051455981",
    "repliedAt": "Thu Sep 11 20:06:04 +0000 2025"
  },
  {
    "url": "https://twitter.com/anyuser/status/1966218939337179467",
    "repliedAt": "Thu Sep 11 20:05:45 +0000 2025"
  },
  {
    "url": "https://twitter.com/anyuser/status/1965912023172305020",
    "repliedAt": "Thu Sep 11 20:05:45 +0000 2025"
  },
  {
    "url": "https://twitter.com/anyuser/status/1966221136204849206",
    "repliedAt": "Thu Sep 11 20:04:41 +0000 2025"
  },
  {
    "url": "https://twitter.com/anyuser/status/1966220811121115401",
    "repliedAt": "Thu Sep 11 20:04:18 +0000 2025"
  },
  {
    "url": "https://twitter.com/anyuser/status/1966200066328117414",
    "repliedAt": "Thu Sep 11 20:01:15 +0000 2025"
  },
  {
    "url": "https://twitter.com/anyuser/status/1966211389439225894",
    "repliedAt": "Thu Sep 11 20:00:17 +0000 2025"
  },
  {
    "url": "https://twitter.com/anyuser/status/1966200603245236509",
    "repliedAt": "Thu Sep 11 19:59:43 +0000 2025"
  },
  {
    "url": "https://twitter.com/anyuser/status/1966194327522259399",
    "repliedAt": "Thu Sep 11 19:59:19 +0000 2025"
  },
  {
    "url": "https://twitter.com/anyuser/status/1966213746109436001",
    "repliedAt": "Thu Sep 11 19:59:05 +0000 2025"
  },
  {
    "url": "https://twitter.com/anyuser/status/1966168666803777671",
    "repliedAt": "Thu Sep 11 19:59:00 +0000 2025"
  },
  {
    "url": "https://twitter.com/anyuser/status/1966200539416613068",
    "repliedAt": "Thu Sep 11 19:58:53 +0000 2025"
  },
  {
    "url": "https://twitter.com/anyuser/status/1966199320526598631",
    "repliedAt": "Thu Sep 11 19:57:18 +0000 2025"
  },
  {
    "url": "https://twitter.com/anyuser/status/1965857256714703046",
    "repliedAt": "Thu Sep 11 19:56:42 +0000 2025"
  },
  {
    "url": "https://twitter.com/anyuser/status/1965859949885665291",
    "repliedAt": "Thu Sep 11 19:50:40 +0000 2025"
  },
  {
    "url": "https://twitter.com/anyuser/status/1966169162922996083",
    "repliedAt": "Thu Sep 11 19:47:46 +0000 2025"
  },
  {
    "url": "https://twitter.com/anyuser/status/1966218569194377656",
    "repliedAt": "Thu Sep 11 19:46:46 +0000 2025"
  },
  {
    "url": "https://twitter.com/anyuser/status/1966180645392232528",
    "repliedAt": "Thu Sep 11 19:39:52 +0000 2025"
  },
  {
    "url": "https://twitter.com/anyuser/status/1965975019273756707",
    "repliedAt": "Thu Sep 11 19:37:55 +0000 2025"
  },
  {
    "url": "https://twitter.com/anyuser/status/1965987667612762337",
    "repliedAt": "Thu Sep 11 19:23:47 +0000 2025"
  },
  {
    "url": "https://twitter.com/anyuser/status/1965926847256187103",
    "repliedAt": "Thu Sep 11 19:21:49 +0000 2025"
  },
  {
    "url": "https://twitter.com/anyuser/status/1966148717796557252",
    "repliedAt": "Thu Sep 11 19:17:26 +0000 2025"
  },
  {
    "url": "https://twitter.com/anyuser/status/1965977907567939781",
    "repliedAt": "Thu Sep 11 19:15:39 +0000 2025"
  },
  {
    "url": "https://twitter.com/anyuser/status/1966168450344357906",
    "repliedAt": "Thu Sep 11 19:14:23 +0000 2025"
  },
  {
    "url": "https://twitter.com/anyuser/status/1965873802963005863",
    "repliedAt": "Thu Sep 11 19:06:52 +0000 2025"
  },
  {
    "url": "https://twitter.com/anyuser/status/1965971480560415147",
    "repliedAt": "Thu Sep 11 19:01:08 +0000 2025"
  },
  {
    "url": "https://twitter.com/anyuser/status/1965871972866511315",
    "repliedAt": "Thu Sep 11 18:58:41 +0000 2025"
  },
  {
    "url": "https://twitter.com/anyuser/status/1965892060076253475",
    "repliedAt": "Thu Sep 11 18:56:20 +0000 2025"
  },
  {
    "url": "https://twitter.com/anyuser/status/1965920659168698845",
    "repliedAt": "Thu Sep 11 18:54:39 +0000 2025"
  },
  {
    "url": "https://twitter.com/anyuser/status/1965769106885668971",
    "repliedAt": "Thu Sep 11 18:53:41 +0000 2025"
  },
  {
    "url": "https://twitter.com/anyuser/status/1966154052657623489",
    "repliedAt": "Thu Sep 11 18:53:38 +0000 2025"
  },
  {
    "url": "https://twitter.com/anyuser/status/1966102132731543555",
    "repliedAt": "Thu Sep 11 18:51:31 +0000 2025"
  },
  {
    "url": "https://twitter.com/anyuser/status/1965919362046636377",
    "repliedAt": "Thu Sep 11 18:45:57 +0000 2025"
  },
  {
    "url": "https://twitter.com/anyuser/status/1965856831043154091",
    "repliedAt": "Thu Sep 11 18:42:21 +0000 2025"
  },
  {
    "url": "https://twitter.com/anyuser/status/1966175269200515236",
    "repliedAt": "Thu Sep 11 18:37:37 +0000 2025"
  },
  {
    "url": "https://twitter.com/anyuser/status/1965878255812219339",
    "repliedAt": "Thu Sep 11 17:46:50 +0000 2025"
  },
  {
    "url": "https://twitter.com/anyuser/status/1965886127359012917",
    "repliedAt": "Thu Sep 11 17:40:26 +0000 2025"
  },
  {
    "url": "https://twitter.com/anyuser/status/1966150696815964213",
    "repliedAt": "Thu Sep 11 17:36:44 +0000 2025"
  },
  {
    "url": "https://twitter.com/anyuser/status/1965996412283265323",
    "repliedAt": "Thu Sep 11 17:22:55 +0000 2025"
  },
  {
    "url": "https://twitter.com/anyuser/status/1966010709549953059",
    "repliedAt": "Thu Sep 11 17:21:13 +0000 2025"
  },
  {
    "url": "https://twitter.com/anyuser/status/1965813896859824498",
    "repliedAt": "Thu Sep 11 17:20:02 +0000 2025"
  },
  {
    "url": "https://twitter.com/anyuser/status/1966152768051359949",
    "repliedAt": "Thu Sep 11 17:15:53 +0000 2025"
  },
  {
    "url": "https://twitter.com/anyuser/status/1966155440431182271",
    "repliedAt": "Thu Sep 11 17:15:19 +0000 2025"
  },
  {
    "url": "https://twitter.com/anyuser/status/1966017026935406600",
    "repliedAt": "Thu Sep 11 17:14:31 +0000 2025"
  },
  {
    "url": "https://twitter.com/anyuser/status/1966179659055616198",
    "repliedAt": "Thu Sep 11 17:11:09 +0000 2025"
  },
  {
    "url": "https://twitter.com/anyuser/status/1966124556369932670",
    "repliedAt": "Thu Sep 11 17:10:46 +0000 2025"
  },
  {
    "url": "https://twitter.com/anyuser/status/1966167625500856786",
    "repliedAt": "Thu Sep 11 17:10:15 +0000 2025"
  },
  {
    "url": "https://twitter.com/anyuser/status/1966170502638215633",
    "repliedAt": "Thu Sep 11 17:10:10 +0000 2025"
  },
  {
    "url": "https://twitter.com/anyuser/status/1966176914927911045",
    "repliedAt": "Thu Sep 11 17:08:55 +0000 2025"
  },
  {
    "url": "https://twitter.com/anyuser/status/1966176312260739094",
    "repliedAt": "Thu Sep 11 17:08:39 +0000 2025"
  },
  {
    "url": "https://twitter.com/anyuser/status/1966184974354440548",
    "repliedAt": "Thu Sep 11 17:08:31 +0000 2025"
  },
  {
    "url": "https://twitter.com/anyuser/status/1966180220228243462",
    "repliedAt": "Thu Sep 11 17:00:45 +0000 2025"
  },
  {
    "url": "https://twitter.com/anyuser/status/1966173221520285959",
    "repliedAt": "Thu Sep 11 16:59:56 +0000 2025"
  },
  {
    "url": "https://twitter.com/anyuser/status/1966169055477506440",
    "repliedAt": "Thu Sep 11 16:59:40 +0000 2025"
  },
  {
    "url": "https://twitter.com/anyuser/status/1966107605358817375",
    "repliedAt": "Thu Sep 11 16:59:21 +0000 2025"
  },
  {
    "url": "https://twitter.com/anyuser/status/1966170873506726281",
    "repliedAt": "Thu Sep 11 16:59:08 +0000 2025"
  },
  {
    "url": "https://twitter.com/anyuser/status/1966171390266253734",
    "repliedAt": "Thu Sep 11 16:57:50 +0000 2025"
  },
  {
    "url": "https://twitter.com/anyuser/status/1966181889544433785",
    "repliedAt": "Thu Sep 11 16:57:07 +0000 2025"
  },
  {
    "url": "https://twitter.com/anyuser/status/1966165058221912301",
    "repliedAt": "Thu Sep 11 16:56:31 +0000 2025"
  }
]